CHANGELOG.rst
MANIFEST.in
README.md
VERSION
setup.cfg
setup.py
LICENSES/AGPL-3.0-only.txt
LICENSES/Apache-2.0.txt
LICENSES/BSD-4-Clause.txt
LICENSES/CC-BY-3.0.txt
LICENSES/CC-BY-SA-4.0.txt
LICENSES/CC0-1.0.txt
LICENSES/GPL-2.0-only.txt
LICENSES/GPL-2.0-or-later.txt
LICENSES/GPL-3.0-only.txt
LICENSES/GPL-3.0-or-later.txt
LICENSES/MIT.txt
LICENSES/OLDAP-2.8.txt
bin/debops
bin/debops-defaults
bin/debops-init
bin/debops-padlock
bin/debops-task
bin/debops-update
debops/__init__.py
debops/config.py
debops/padlock-script
debops.egg-info/PKG-INFO
debops.egg-info/SOURCES.txt
debops.egg-info/dependency_links.txt
debops.egg-info/requires.txt
debops.egg-info/top_level.txt
debops.egg-info/zip-safe
debops/ansible/debops-contrib-playbooks/README.rst
debops/ansible/debops-contrib-playbooks/service/all.yml
debops/ansible/debops-contrib-playbooks/service/apparmor.yml
debops/ansible/debops-contrib-playbooks/service/apt_cacher_ng.yml
debops/ansible/debops-contrib-playbooks/service/bitcoind.yml
debops/ansible/debops-contrib-playbooks/service/btrfs.yml
debops/ansible/debops-contrib-playbooks/service/dnsmasq.yml
debops/ansible/debops-contrib-playbooks/service/firejail.yml
debops/ansible/debops-contrib-playbooks/service/foodsoft-nginx.yml
debops/ansible/debops-contrib-playbooks/service/foodsoft.yml
debops/ansible/debops-contrib-playbooks/service/fuse.yml
debops/ansible/debops-contrib-playbooks/service/homeassistant-nginx.yml
debops/ansible/debops-contrib-playbooks/service/homeassistant-plain.yml
debops/ansible/debops-contrib-playbooks/service/homeassistant.yml
debops/ansible/debops-contrib-playbooks/service/kodi.yml
debops/ansible/debops-contrib-playbooks/service/snapshot_snapper.yml
debops/ansible/debops-contrib-playbooks/service/tor.yml
debops/ansible/debops-contrib-playbooks/service/volkszaehler-apache.yml
debops/ansible/debops-contrib-playbooks/service/volkszaehler-nginx.yml
debops/ansible/debops-contrib-playbooks/service/volkszaehler.yml
debops/ansible/debops-contrib-playbooks/service/x2go_server.yml
debops/ansible/playbooks/COPYRIGHT
debops/ansible/playbooks/agent.yml
debops/ansible/playbooks/app.yml
debops/ansible/playbooks/bootstrap-ldap.yml
