Metadata-Version: 2.1
Name: debops
Version: 2.3.10
Summary: Your Debian-based data center in a box
Home-page: https://debops.org/
Download-URL: https://github.com/debops/debops/archive/v2.3.10.tar.gz
Author: DebOps Developers
Author-email: debops-users@lists.debops.org
License: GPL-3.0-or-later
Keywords: ansible debian sysadmin
Classifier: Development Status :: 5 - Production/Stable
Classifier: Environment :: Console
Classifier: Intended Audience :: Information Technology
Classifier: Intended Audience :: System Administrators
Classifier: License :: OSI Approved :: GNU General Public License v3 or later (GPLv3+)
Classifier: Natural Language :: English
Classifier: Operating System :: POSIX
Classifier: Programming Language :: Other Scripting Engines
Classifier: Programming Language :: Python
Classifier: Programming Language :: Python :: 2
Classifier: Programming Language :: Python :: 2.7
Classifier: Programming Language :: Python :: 3
Classifier: Programming Language :: Python :: 3.5
Classifier: Programming Language :: Python :: 3.6
Classifier: Topic :: System :: Installation/Setup
Classifier: Topic :: System :: Systems Administration
Classifier: Topic :: Utilities
Requires-Python: >=2.7, !=3.0.*, !=3.1.*, !=3.2.*, !=3.3.*, !=3.4.*, <4
Provides-Extra: ansible
License-File: LICENSES/OLDAP-2.8.txt
License-File: LICENSES/CC-BY-3.0.txt
License-File: LICENSES/Apache-2.0.txt
License-File: LICENSES/BSD-4-Clause.txt
License-File: LICENSES/CC-BY-SA-4.0.txt
License-File: LICENSES/MIT.txt
License-File: LICENSES/AGPL-3.0-only.txt
License-File: LICENSES/GPL-2.0-or-later.txt
License-File: LICENSES/CC0-1.0.txt
License-File: LICENSES/GPL-3.0-only.txt
License-File: LICENSES/GPL-3.0-or-later.txt
License-File: LICENSES/GPL-2.0-only.txt
